[
    {
        "y": 7,
        "bowler": "DR Smith"
    },
    {
        "y": 6.923076923076923,
        "bowler": "Gurkeerat Singh"
    },
    {
        "y": 6.8,
        "bowler": "Parvez Rasool"
    },
    {
        "y": 6.75,
        "bowler": "S Nadeem"
    },
    {
        "y": 6.666666666666667,
        "bowler": "DJG Sammy"
    },
    {
        "y": 6.5280000000000005,
        "bowler": "GB Hogg"
    },
    {
        "y": 6.473684210526316,
        "bowler": "R Ashwin"
    },
    {
        "y": 6.428571428571429,
        "bowler": "DJ Muthuswami"
    },
    {
        "y": 4.8,
        "bowler": "RN ten Doeschate"
    },
    {
        "y": 4.428571428571429,
        "bowler": "J Yadav"
    }
]